PSD_Generator/__init__.py
PSD_Generator/processor.py
tests/__init__.py
tests/test_processor.py
PSD_Generator-0.1.0.dist-info/LICENSE
PSD_Generator-0.1.0.dist-info/METADATA
PSD_Generator-0.1.0.dist-info/WHEEL
PSD_Generator-0.1.0.dist-info/top_level.txt
PSD_Generator-0.1.0.dist-info/RECORD
