Metadata-Version: 2.1
Name: PSD-Generator
Version: 0.1.0
Summary: A library for processing images and saving layers as PSD
Home-page: https://github.com/yatharth-doshi/PSD_Generator
Author: Yatharth Doshi
Author-email: yatharthdoshi4@gmail.com
Classifier: Programming Language :: Python :: 3
Classifier: License :: OSI Approved :: MIT License
Classifier: Operating System :: OS Independent
Requires-Python: >=3.9
License-File: LICENSE
Requires-Dist: numpy
Requires-Dist: colorthief
Requires-Dist: scikit-learn
Requires-Dist: Pillow
Requires-Dist: colormath
Requires-Dist: wand
